konnektr_graph/__init__.py
konnektr_graph/client.py
konnektr_graph/exceptions.py
konnektr_graph/models.py
konnektr_graph/py.typed
konnektr_graph/aio/__init__.py
konnektr_graph/aio/client.py
konnektr_graph/auth/__init__.py
konnektr_graph/auth/async_client_secret_credential.py
konnektr_graph/auth/async_device_code_credential.py
konnektr_graph/auth/client_secret_credential.py
konnektr_graph/auth/device_code_credential.py
konnektr_graph/auth/protocol.py
konnektr_graph/auth/static_token_credential.py
konnektr_graph-0.1.4.dist-info/licenses/LICENSE
konnektr_graph-0.1.4.dist-info/METADATA
konnektr_graph-0.1.4.dist-info/WHEEL
konnektr_graph-0.1.4.dist-info/top_level.txt
konnektr_graph-0.1.4.dist-info/RECORD
