Metadata-Version: 2.4
Name: konnektr-graph
Version: 0.1.4
Summary: Konnektr Graph SDK for Python
Author-email: Konnektr <info@konnektr.io>
Project-URL: Homepage, https://github.com/konnektr-io/graph-client-sdk-python
Project-URL: Bug Tracker, https://github.com/konnektr-io/graph-client-sdk-python/issues
Classifier: Programming Language :: Python :: 3
Classifier: License :: OSI Approved :: MIT License
Classifier: Operating System :: OS Independent
Classifier: Development Status :: 4 - Beta
Classifier: Intended Audience :: Developers
Classifier: Topic :: Software Development :: Libraries :: Python Modules
Requires-Python: >=3.8
License-File: LICENSE
Requires-Dist: requests>=2.28.0
Requires-Dist: aiohttp>=3.8.0
Provides-Extra: docs
Requires-Dist: pydoc-markdown[novella]>=4.8.2; extra == "docs"
Dynamic: license-file
